pyplace/__init__.py
pyplace/container.py
pyplace/pbp.py
pyplace/psc.py
pyplace-0.6.11.dist-info/LICENSE
pyplace-0.6.11.dist-info/METADATA
pyplace-0.6.11.dist-info/WHEEL
pyplace-0.6.11.dist-info/top_level.txt
pyplace-0.6.11.dist-info/RECORD
