Metadata-Version: 2.1
Name: pyplace
Version: 0.6.11
Summary: A littler utility to stop remembering tons of numbers and star using percentages for containers size and placement.
Home-page: https://volatileprogramming.org
Author: Jeffrey I. Jose
Author-email: jeffrey@volatileprogramming.org
License: GNU
Project-URL: Source Code, https://github.com/volatile-programming/pyplace
Platform: UNKNOWN
Classifier: Programming Language :: Python :: 3
Classifier: License :: OSI Approved :: GNU Affero General Public License v3
Classifier: Development Status :: 3 - Alpha
Classifier: Operating System :: OS Independent
Requires-Python: >=3.6
